odoo/addons/project_forecast_line_bokeh_chart/README.rst
odoo/addons/project_forecast_line_bokeh_chart/__init__.py
odoo/addons/project_forecast_line_bokeh_chart/__manifest__.py
odoo/addons/project_forecast_line_bokeh_chart/i18n/fr.po
odoo/addons/project_forecast_line_bokeh_chart/i18n/project_forecast_line_bokeh_chart.pot
odoo/addons/project_forecast_line_bokeh_chart/models/__init__.py
odoo/addons/project_forecast_line_bokeh_chart/models/forecast_line.py
odoo/addons/project_forecast_line_bokeh_chart/readme/CONTRIBUTORS.rst
odoo/addons/project_forecast_line_bokeh_chart/readme/DESCRIPTION.rst
odoo/addons/project_forecast_line_bokeh_chart/report/__init__.py
odoo/addons/project_forecast_line_bokeh_chart/report/forecast_line_reporting.py
odoo/addons/project_forecast_line_bokeh_chart/report/forecast_line_reporting_views.xml
odoo/addons/project_forecast_line_bokeh_chart/security/ir.model.access.csv
odoo/addons/project_forecast_line_bokeh_chart/static/description/icon.png
odoo/addons/project_forecast_line_bokeh_chart/static/description/index.html
odoo14_addon_project_forecast_line_bokeh_chart-14.0.1.0.2.dist-info/METADATA
odoo14_addon_project_forecast_line_bokeh_chart-14.0.1.0.2.dist-info/WHEEL
odoo14_addon_project_forecast_line_bokeh_chart-14.0.1.0.2.dist-info/top_level.txt
odoo14_addon_project_forecast_line_bokeh_chart-14.0.1.0.2.dist-info/RECORD
