Metadata-Version: 2.1
Name: odoo14-addon-project_forecast_line_bokeh_chart
Version: 14.0.1.0.2
Summary: Project Forecast Lines Bokeh Chart
Home-page: https://github.com/OCA/project
Author: Camptocamp, Odoo Community Association (OCA)
Author-email: support@odoo-community.org
License: AGPL-3
Classifier: Programming Language :: Python
Classifier: Framework :: Odoo
Classifier: Framework :: Odoo :: 14.0
Classifier: License :: OSI Approved :: GNU Affero General Public License v3
Classifier: Development Status :: 3 - Alpha
Requires-Python: >=3.6
Requires-Dist: odoo14-addon-project-forecast-line
Requires-Dist: odoo14-addon-web-widget-bokeh-chart
Requires-Dist: odoo<14.1dev,>=14.0a
